CONTRIBUTING.rst
HISTORY.rst
LICENSE
MANIFEST.in
README.rst
setup.cfg
setup.py
docs/Makefile
docs/conf.py
docs/contributing.rst
docs/history.rst
docs/index.rst
docs/installation.rst
docs/make.bat
docs/readme.rst
docs/usage.rst
korrelated/__init__.py
korrelated/korrelated.py
korrelated.egg-info/PKG-INFO
korrelated.egg-info/SOURCES.txt
korrelated.egg-info/dependency_links.txt
korrelated.egg-info/not-zip-safe
korrelated.egg-info/top_level.txt
tests/__init__.py
tests/test_korrelated.py