Metadata-Version: 1.2
Name: korrelated
Version: 0.1.0
Summary: A package containing python interfaces to some popular correlated-k radiative transfer libraries
Home-page: https://github.com/JoyMonteiro/korrelated
Author: Joy Merwin Monteiro
Author-email: joy.merwin@gmail.com
License: BSD license
Keywords: korrelated
Platform: UNKNOWN
Classifier: Development Status :: 2 - Pre-Alpha
Classifier: Intended Audience :: Developers
Classifier: License :: OSI Approved :: BSD License
Classifier: Natural Language :: English
Classifier: Programming Language :: Python :: 3
Classifier: Programming Language :: Python :: 3.5
Classifier: Programming Language :: Python :: 3.6
Classifier: Programming Language :: Python :: 3.7
Classifier: Programming Language :: Python :: 3.8
Requires-Python: >=3.5
